<?xml version="1.0" encoding="utf-8"?>
<TextureAtlas imagePath="auxxy.png">
	<!-- Created with Adobe Animate version 22.0.0.93 -->
	<!-- http://www.adobe.com/products/animate.html -->
	<SubTexture name="cald-alt0000" x="2" y="2" width="1218" height="875" frameX="-44" frameY="0" frameWidth="1284" frameHeight="875"/>
	<SubTexture name="cald-alt0001" x="1222" y="2" width="1278" height="614" frameX="-6" frameY="-261" frameWidth="1284" frameHeight="875"/>
	<SubTexture name="cald-alt0002" x="2502" y="2" width="1278" height="614" frameX="-6" frameY="-261" frameWidth="1284" frameHeight="875"/>
	<SubTexture name="cald-alt0003" x="3782" y="2" width="1258" height="618" frameX="0" frameY="-257" frameWidth="1284" frameHeight="875"/>
	<SubTexture name="cald-alt0004" x="5042" y="2" width="1258" height="618" frameX="0" frameY="-257" frameWidth="1284" frameHeight="875"/>
	<SubTexture name="cald-alt0005" x="6302" y="2" width="1192" height="616" frameX="-59" frameY="-259" frameWidth="1284" frameHeight="875"/>
	<SubTexture name="cald-alt0006" x="2" y="879" width="1192" height="616" frameX="-59" frameY="-259" frameWidth="1284" frameHeight="875"/>
	<SubTexture name="cald-alt0007" x="1196" y="879" width="889" height="616" frameX="-163" frameY="-259" frameWidth="1284" frameHeight="875"/>
	<SubTexture name="cald-alt0008" x="2087" y="879" width="889" height="616" frameX="-163" frameY="-259" frameWidth="1284" frameHeight="875"/>
	<SubTexture name="cald-alt0009" x="2087" y="879" width="889" height="616" frameX="-163" frameY="-259" frameWidth="1284" frameHeight="875"/>
	<SubTexture name="cald-alt0010" x="2978" y="879" width="889" height="616" frameX="-163" frameY="-259" frameWidth="1284" frameHeight="875"/>
	<SubTexture name="cald-alt0011" x="2978" y="879" width="889" height="616" frameX="-163" frameY="-259" frameWidth="1284" frameHeight="875"/>
	<SubTexture name="cald-alt0012" x="2978" y="879" width="889" height="616" frameX="-163" frameY="-259" frameWidth="1284" frameHeight="875"/>
	<SubTexture name="cald-alt0013" x="2978" y="879" width="889" height="616" frameX="-163" frameY="-259" frameWidth="1284" frameHeight="875"/>
	<SubTexture name="cald-alt0014" x="2978" y="879" width="889" height="616" frameX="-163" frameY="-259" frameWidth="1284" frameHeight="875"/>
	<SubTexture name="caldown0000" x="3869" y="879" width="850" height="573" frameX="-8" frameY="0" frameWidth="858" frameHeight="573"/>
	<SubTexture name="caldown0001" x="4721" y="879" width="858" height="569" frameX="0" frameY="-4" frameWidth="858" frameHeight="573"/>
	<SubTexture name="caldown0002" x="5581" y="879" width="854" height="569" frameX="-4" frameY="-4" frameWidth="858" frameHeight="573"/>
	<SubTexture name="caldown0003" x="6437" y="879" width="853" height="569" frameX="-5" frameY="-4" frameWidth="858" frameHeight="573"/>
	<SubTexture name="caldown0004" x="7292" y="879" width="853" height="569" frameX="-5" frameY="-4" frameWidth="858" frameHeight="573"/>
	<SubTexture name="caldown0005" x="2" y="1497" width="843" height="569" frameX="-15" frameY="-4" frameWidth="858" frameHeight="573"/>
	<SubTexture name="caldown0006" x="847" y="1497" width="843" height="569" frameX="-15" frameY="-4" frameWidth="858" frameHeight="573"/>
	<SubTexture name="caldown0007" x="847" y="1497" width="843" height="569" frameX="-15" frameY="-4" frameWidth="858" frameHeight="573"/>
	<SubTexture name="caldown0008" x="1692" y="1497" width="843" height="569" frameX="-15" frameY="-4" frameWidth="858" frameHeight="573"/>
	<SubTexture name="caldown0009" x="1692" y="1497" width="843" height="569" frameX="-15" frameY="-4" frameWidth="858" frameHeight="573"/>
	<SubTexture name="caldown0010" x="2537" y="1497" width="843" height="569" frameX="-15" frameY="-4" frameWidth="858" frameHeight="573"/>
	<SubTexture name="caldown0011" x="2537" y="1497" width="843" height="569" frameX="-15" frameY="-4" frameWidth="858" frameHeight="573"/>
	<SubTexture name="caldown0012" x="2537" y="1497" width="843" height="569" frameX="-15" frameY="-4" frameWidth="858" frameHeight="573"/>
	<SubTexture name="caldown0013" x="2537" y="1497" width="843" height="569" frameX="-15" frameY="-4" frameWidth="858" frameHeight="573"/>
	<SubTexture name="caldown0014" x="2537" y="1497" width="843" height="569" frameX="-15" frameY="-4" frameWidth="858" frameHeight="573"/>
	<SubTexture name="calidle0000" x="3382" y="1497" width="1113" height="671" frameX="-34" frameY="-38" frameWidth="1147" frameHeight="709"/>
	<SubTexture name="calidle0001" x="4497" y="1497" width="1113" height="671" frameX="-34" frameY="-38" frameWidth="1147" frameHeight="709"/>
	<SubTexture name="calidle0002" x="5612" y="1497" width="1109" height="680" frameX="-34" frameY="-29" frameWidth="1147" frameHeight="709"/>
	<SubTexture name="calidle0003" x="6723" y="1497" width="1109" height="680" frameX="-34" frameY="-29" frameWidth="1147" frameHeight="709"/>
	<SubTexture name="calidle0004" x="2" y="2179" width="1096" height="693" frameX="-33" frameY="-16" frameWidth="1147" frameHeight="709"/>
	<SubTexture name="calidle0005" x="1100" y="2179" width="1095" height="693" frameX="-34" frameY="-16" frameWidth="1147" frameHeight="709"/>
	<SubTexture name="calidle0006" x="2197" y="2179" width="1086" height="707" frameX="-37" frameY="-2" frameWidth="1147" frameHeight="709"/>
	<SubTexture name="calidle0007" x="3285" y="2179" width="1085" height="707" frameX="-38" frameY="-2" frameWidth="1147" frameHeight="709"/>
	<SubTexture name="calidle0008" x="4372" y="2179" width="1121" height="708" frameX="0" frameY="-1" frameWidth="1147" frameHeight="709"/>
	<SubTexture name="calidle0009" x="5495" y="2179" width="1121" height="708" frameX="0" frameY="-1" frameWidth="1147" frameHeight="709"/>
	<SubTexture name="calidle0010" x="6618" y="2179" width="1079" height="709" frameX="-42" frameY="0" frameWidth="1147" frameHeight="709"/>
	<SubTexture name="calidle0011" x="6618" y="2179" width="1079" height="709" frameX="-42" frameY="0" frameWidth="1147" frameHeight="709"/>
	<SubTexture name="calidle0012" x="2" y="2890" width="1079" height="709" frameX="-42" frameY="0" frameWidth="1147" frameHeight="709"/>
	<SubTexture name="calidle0013" x="1083" y="2890" width="1083" height="709" frameX="-42" frameY="0" frameWidth="1147" frameHeight="709"/>
	<SubTexture name="calidle0014" x="1083" y="2890" width="1083" height="709" frameX="-42" frameY="0" frameWidth="1147" frameHeight="709"/>
	<SubTexture name="call-alt0000" x="2168" y="2890" width="1053" height="775" frameX="-89" frameY="0" frameWidth="1142" frameHeight="775"/>
	<SubTexture name="call-alt0001" x="3223" y="2890" width="1134" height="723" frameX="-8" frameY="-52" frameWidth="1142" frameHeight="775"/>
	<SubTexture name="call-alt0002" x="4359" y="2890" width="1134" height="723" frameX="-8" frameY="-52" frameWidth="1142" frameHeight="775"/>
	<SubTexture name="call-alt0003" x="5495" y="2890" width="1141" height="706" frameX="0" frameY="-69" frameWidth="1142" frameHeight="775"/>
	<SubTexture name="call-alt0004" x="6638" y="2890" width="1141" height="706" frameX="0" frameY="-69" frameWidth="1142" frameHeight="775"/>
	<SubTexture name="call-alt0005" x="2" y="3667" width="954" height="706" frameX="-187" frameY="-69" frameWidth="1142" frameHeight="775"/>
	<SubTexture name="call-alt0006" x="958" y="3667" width="935" height="706" frameX="-206" frameY="-69" frameWidth="1142" frameHeight="775"/>
	<SubTexture name="call-alt0007" x="1895" y="3667" width="935" height="706" frameX="-206" frameY="-69" frameWidth="1142" frameHeight="775"/>
	<SubTexture name="call-alt0008" x="1895" y="3667" width="935" height="706" frameX="-206" frameY="-69" frameWidth="1142" frameHeight="775"/>
	<SubTexture name="call-alt0009" x="2832" y="3667" width="935" height="706" frameX="-206" frameY="-69" frameWidth="1142" frameHeight="775"/>
	<SubTexture name="call-alt0010" x="2832" y="3667" width="935" height="706" frameX="-206" frameY="-69" frameWidth="1142" frameHeight="775"/>
	<SubTexture name="call-alt0011" x="3769" y="3667" width="935" height="706" frameX="-206" frameY="-69" frameWidth="1142" frameHeight="775"/>
	<SubTexture name="call-alt0012" x="3769" y="3667" width="935" height="706" frameX="-206" frameY="-69" frameWidth="1142" frameHeight="775"/>
	<SubTexture name="call-alt0013" x="3769" y="3667" width="935" height="706" frameX="-206" frameY="-69" frameWidth="1142" frameHeight="775"/>
	<SubTexture name="call-alt0014" x="3769" y="3667" width="935" height="706" frameX="-206" frameY="-69" frameWidth="1142" frameHeight="775"/>
	<SubTexture name="calleft0000" x="4706" y="3667" width="906" height="718"/>
	<SubTexture name="calleft0001" x="5614" y="3667" width="903" height="705" frameX="-3" frameY="-13" frameWidth="906" frameHeight="718"/>
	<SubTexture name="calleft0002" x="6519" y="3667" width="905" height="705" frameX="-1" frameY="-13" frameWidth="906" frameHeight="718"/>
	<SubTexture name="calleft0003" x="2" y="4387" width="903" height="705" frameX="-3" frameY="-13" frameWidth="906" frameHeight="718"/>
	<SubTexture name="calleft0004" x="907" y="4387" width="903" height="705" frameX="-3" frameY="-13" frameWidth="906" frameHeight="718"/>
	<SubTexture name="calleft0005" x="1812" y="4387" width="903" height="705" frameX="-3" frameY="-13" frameWidth="906" frameHeight="718"/>
	<SubTexture name="calleft0006" x="2717" y="4387" width="884" height="705" frameX="-22" frameY="-13" frameWidth="906" frameHeight="718"/>
	<SubTexture name="calleft0007" x="3603" y="4387" width="884" height="705" frameX="-22" frameY="-13" frameWidth="906" frameHeight="718"/>
	<SubTexture name="calleft0008" x="3603" y="4387" width="884" height="705" frameX="-22" frameY="-13" frameWidth="906" frameHeight="718"/>
	<SubTexture name="calleft0009" x="4489" y="4387" width="884" height="705" frameX="-22" frameY="-13" frameWidth="906" frameHeight="718"/>
	<SubTexture name="calleft0010" x="4489" y="4387" width="884" height="705" frameX="-22" frameY="-13" frameWidth="906" frameHeight="718"/>
	<SubTexture name="calleft0011" x="5375" y="4387" width="884" height="705" frameX="-22" frameY="-13" frameWidth="906" frameHeight="718"/>
	<SubTexture name="calleft0012" x="5375" y="4387" width="884" height="705" frameX="-22" frameY="-13" frameWidth="906" frameHeight="718"/>
	<SubTexture name="calleft0013" x="5375" y="4387" width="884" height="705" frameX="-22" frameY="-13" frameWidth="906" frameHeight="718"/>
	<SubTexture name="calleft0014" x="5375" y="4387" width="884" height="705" frameX="-22" frameY="-13" frameWidth="906" frameHeight="718"/>
	<SubTexture name="calr-alt0000" x="6261" y="4387" width="1075" height="720" frameX="0" frameY="-15" frameWidth="1311" frameHeight="735"/>
	<SubTexture name="calr-alt0001" x="2" y="5109" width="1211" height="735" frameX="0" frameY="0" frameWidth="1311" frameHeight="735"/>
	<SubTexture name="calr-alt0002" x="1215" y="5109" width="1211" height="735" frameX="0" frameY="0" frameWidth="1311" frameHeight="735"/>
	<SubTexture name="calr-alt0003" x="2428" y="5109" width="1293" height="716" frameX="0" frameY="-19" frameWidth="1311" frameHeight="735"/>
	<SubTexture name="calr-alt0004" x="2428" y="5109" width="1293" height="716" frameX="0" frameY="-19" frameWidth="1311" frameHeight="735"/>
	<SubTexture name="calr-alt0005" x="3723" y="5109" width="1311" height="716" frameX="0" frameY="-19" frameWidth="1311" frameHeight="735"/>
	<SubTexture name="calr-alt0006" x="5036" y="5109" width="760" height="716" frameX="0" frameY="-19" frameWidth="1311" frameHeight="735"/>
	<SubTexture name="calr-alt0007" x="5036" y="5109" width="760" height="716" frameX="0" frameY="-19" frameWidth="1311" frameHeight="735"/>
	<SubTexture name="calr-alt0008" x="5036" y="5109" width="760" height="716" frameX="0" frameY="-19" frameWidth="1311" frameHeight="735"/>
	<SubTexture name="calr-alt0009" x="5036" y="5109" width="760" height="716" frameX="0" frameY="-19" frameWidth="1311" frameHeight="735"/>
	<SubTexture name="calr-alt0010" x="5036" y="5109" width="760" height="716" frameX="0" frameY="-19" frameWidth="1311" frameHeight="735"/>
	<SubTexture name="calr-alt0011" x="5036" y="5109" width="760" height="716" frameX="0" frameY="-19" frameWidth="1311" frameHeight="735"/>
	<SubTexture name="calr-alt0012" x="5036" y="5109" width="760" height="716" frameX="0" frameY="-19" frameWidth="1311" frameHeight="735"/>
	<SubTexture name="calr-alt0013" x="5036" y="5109" width="760" height="716" frameX="0" frameY="-19" frameWidth="1311" frameHeight="735"/>
	<SubTexture name="calr-alt0014" x="5036" y="5109" width="760" height="716" frameX="0" frameY="-19" frameWidth="1311" frameHeight="735"/>
	<SubTexture name="calright0000" x="5798" y="5109" width="715" height="719"/>
	<SubTexture name="calright0001" x="6515" y="5109" width="715" height="715" frameX="0" frameY="-4" frameWidth="715" frameHeight="719"/>
	<SubTexture name="calright0002" x="7232" y="5109" width="715" height="715" frameX="0" frameY="-4" frameWidth="715" frameHeight="719"/>
	<SubTexture name="calright0003" x="2" y="5846" width="715" height="715" frameX="0" frameY="-4" frameWidth="715" frameHeight="719"/>
	<SubTexture name="calright0004" x="719" y="5846" width="715" height="715" frameX="0" frameY="-4" frameWidth="715" frameHeight="719"/>
	<SubTexture name="calright0005" x="1436" y="5846" width="715" height="715" frameX="0" frameY="-4" frameWidth="715" frameHeight="719"/>
	<SubTexture name="calright0006" x="2153" y="5846" width="715" height="715" frameX="0" frameY="-4" frameWidth="715" frameHeight="719"/>
	<SubTexture name="calright0007" x="2870" y="5846" width="715" height="715" frameX="0" frameY="-4" frameWidth="715" frameHeight="719"/>
	<SubTexture name="calright0008" x="3587" y="5846" width="715" height="715" frameX="0" frameY="-4" frameWidth="715" frameHeight="719"/>
	<SubTexture name="calright0009" x="2153" y="5846" width="715" height="715" frameX="0" frameY="-4" frameWidth="715" frameHeight="719"/>
	<SubTexture name="calright0010" x="4304" y="5846" width="715" height="715" frameX="0" frameY="-4" frameWidth="715" frameHeight="719"/>
	<SubTexture name="calright0011" x="2153" y="5846" width="715" height="715" frameX="0" frameY="-4" frameWidth="715" frameHeight="719"/>
	<SubTexture name="calright0012" x="5021" y="5846" width="715" height="715" frameX="0" frameY="-4" frameWidth="715" frameHeight="719"/>
	<SubTexture name="calright0013" x="5021" y="5846" width="715" height="715" frameX="0" frameY="-4" frameWidth="715" frameHeight="719"/>
	<SubTexture name="calright0014" x="5021" y="5846" width="715" height="715" frameX="0" frameY="-4" frameWidth="715" frameHeight="719"/>
	<SubTexture name="calu-alt0000" x="5738" y="5846" width="1370" height="880" frameX="-147" frameY="0" frameWidth="1543" frameHeight="880"/>
	<SubTexture name="calu-alt0001" x="2" y="6728" width="1515" height="861" frameX="-28" frameY="-19" frameWidth="1543" frameHeight="880"/>
	<SubTexture name="calu-alt0002" x="1519" y="6728" width="1515" height="858" frameX="-28" frameY="-22" frameWidth="1543" frameHeight="880"/>
	<SubTexture name="calu-alt0003" x="3036" y="6728" width="1477" height="853" frameX="0" frameY="-27" frameWidth="1543" frameHeight="880"/>
	<SubTexture name="calu-alt0004" x="4515" y="6728" width="1477" height="852" frameX="0" frameY="-28" frameWidth="1543" frameHeight="880"/>
	<SubTexture name="calu-alt0005" x="5994" y="6728" width="857" height="855" frameX="-443" frameY="-25" frameWidth="1543" frameHeight="880"/>
	<SubTexture name="calu-alt0006" x="6853" y="6728" width="857" height="849" frameX="-443" frameY="-31" frameWidth="1543" frameHeight="880"/>
	<SubTexture name="calu-alt0007" x="6853" y="6728" width="857" height="849" frameX="-443" frameY="-31" frameWidth="1543" frameHeight="880"/>
</TextureAtlas>
